middleware/__init__.py
middleware/protect.py
capstoneproject2024_common-0.1.0.dist-info/METADATA
capstoneproject2024_common-0.1.0.dist-info/WHEEL
capstoneproject2024_common-0.1.0.dist-info/top_level.txt
capstoneproject2024_common-0.1.0.dist-info/RECORD
