Metadata-Version: 2.1
Name: capstoneproject2024-common
Version: 0.1.0
Summary: Reuse code for FastAPI
Home-page: UNKNOWN
License: UNKNOWN
Platform: UNKNOWN
Requires-Python: >=3.6
Requires-Dist: python-jose
Requires-Dist: python-dotenv
Requires-Dist: fastapi
